skiio/__init__.py
skiio/__main__.py
skiio/_compiler_purr.py
skiio/_compiler_ski.py
skiio/_exceptions.py
skiio/_interpreter.py
skiio/_rule.py
skiio/_skinode.py
skiio/utils/__init__.py
skiio/utils/skibyte.py
skiio-1.0.2.dist-info/LICENSE
skiio-1.0.2.dist-info/WHEEL
skiio-1.0.2.dist-info/METADATA
skiio-1.0.2.dist-info/RECORD
