Metadata-Version: 2.1
Name: skiio
Version: 1.0.2
Summary: An esolang that extends SKI combinators with I/O. Interpreter and Compiler from lambda expressions implemented
License: MIT
Author: Julia
Author-email: julia.poo.poo.poo@gmail.com
Requires-Python: >=3.8,<4.0
Classifier: License :: OSI Approved :: MIT License
Classifier: Programming Language :: Python :: 3
Classifier: Programming Language :: Python :: 3.10
Classifier: Programming Language :: Python :: 3.8
Classifier: Programming Language :: Python :: 3.9
